LagRochePlot/LagRoche.py
LagRochePlot/__init__.py
LagRochePlot-1.2.1.dist-info/LICENSE
LagRochePlot-1.2.1.dist-info/METADATA
LagRochePlot-1.2.1.dist-info/WHEEL
LagRochePlot-1.2.1.dist-info/top_level.txt
LagRochePlot-1.2.1.dist-info/RECORD
