Metadata-Version: 2.1
Name: LagRochePlot
Version: 1.2.1
Summary: Herramienta gráfica para visualizar los puntos de Lagrange y potencial de Roche.
Home-page: https://github.com/Thomas-thief/LagRochePlot
Author: Thomas Salazar, Esteban Sanchez, Sebastian Lopez, Andres Rumillanca
License: MIT
License-File: LICENSE
Requires-Dist: numpy
Requires-Dist: matplotlib
Requires-Dist: pyastronomy
